safla/__init__.py
safla/__main__.py
safla/cli.py
safla/cli_implementations.py
safla/cli_interactive.py
safla/cli_main.py
safla/cli_manager.py
safla/exceptions.py
safla/installer.py
safla/mcp_stdio_server.py
safla/py.typed
safla/api/enhanced_endpoints.py
safla/auth/__init__.py
safla/auth/auth_middleware.py
safla/auth/exceptions.py
safla/auth/jwt_manager.py
safla/core/__init__.py
safla/core/adaptive_safety_boundaries.py
safla/core/auto_scaling_infrastructure.py
safla/core/delta_evaluation.py
safla/core/delta_evaluation_backup.py
safla/core/distributed_mcp_orchestration.py
safla/core/federated_learning_integration.py
safla/core/hybrid_memory.py
safla/core/mcp_orchestration.py
safla/core/mcp_orchestration_backup.py
safla/core/memory_optimizations.py
safla/core/meta_cognitive_engine.py
safla/core/ml_neural_embedding_engine.py
safla/core/ml_neural_embedding_engine_new.py
safla/core/ml_rl_optimizer.py
safla/core/optimized_serialization.py
safla/core/optimized_vector_memory.py
safla/core/safety_validation.py
safla/core/safety_validation_backup.py
safla/core/memory/__init__.py
safla/core/memory/base.py
safla/core/memory/episodic.py
safla/core/memory/hybrid.py
safla/core/memory/semantic.py
safla/core/memory/vector.py
safla/core/memory/working.py
safla/core/metacognitive/__init__.py
safla/core/metacognitive/awareness.py
safla/core/metacognitive/engine.py
safla/core/metacognitive/learning.py
safla/core/metacognitive/metrics.py
safla/core/metacognitive/strategies.py
safla/core/ml/__init__.py
safla/core/ml/base.py
safla/core/ml/engine.py
safla/core/ml/models.py
safla/core/ml/optimizer.py
safla/core/ml/transfer.py
safla/core/ml/versioning.py
safla/integrations/__init__.py
safla/integrations/fastmcp_adapter.py
safla/integrations/fastmcp_client.py
safla/integrations/fastmcp_helpers.py
safla/integrations/fastmcp_server.py
safla/mcp/__init__.py
safla/mcp/handler_registry.py
safla/mcp/server.py
safla/mcp/handlers/__init__.py
safla/mcp/handlers/admin.py
safla/mcp/handlers/agent.py
safla-0.1.3.dist-info/licenses/LICENSE
safla-0.1.3.dist-info/METADATA
safla-0.1.3.dist-info/WHEEL
safla-0.1.3.dist-info/entry_points.txt
safla-0.1.3.dist-info/top_level.txt
safla-0.1.3.dist-info/RECORD
