Metadata-Version: 2.4
Name: safla
Version: 0.1.3
Summary: Self-Aware Feedback Loop Algorithm - A sophisticated AI/ML system implementing autonomous learning and adaptation
Home-page: https://github.com/ruvnet/SAFLA
Author: SAFLA Development Team
Author-email: SAFLA Development Team <dev@safla.ai>
Maintainer-email: SAFLA Development Team <dev@safla.ai>
License-Expression: MIT
Project-URL: Homepage, https://github.com/ruvnet/SAFLA
Project-URL: Documentation, https://safla.readthedocs.io
Project-URL: Repository, https://github.com/ruvnet/SAFLA
Project-URL: Bug Tracker, https://github.com/ruvnet/SAFLA/issues
Project-URL: Changelog, https://github.com/ruvnet/SAFLA/blob/main/CHANGELOG.md
Keywords: ai,machine-learning,autonomous-systems,meta-cognitive,memory-architecture,safety-validation,mcp,self-aware
Classifier: Development Status :: 4 - Beta
Classifier: Intended Audience :: Developers
Classifier: Intended Audience :: Science/Research
Classifier: Operating System :: OS Independent
Classifier: Programming Language :: Python :: 3
Classifier: Programming Language :: Python :: 3.8
Classifier: Programming Language :: Python :: 3.9
Classifier: Programming Language :: Python :: 3.10
Classifier: Programming Language :: Python :: 3.11
Classifier: Programming Language :: Python :: 3.12
Classifier: Topic :: Scientific/Engineering :: Artificial Intelligence
Classifier: Topic :: Software Development :: Libraries :: Python Modules
Classifier: Topic :: System :: Distributed Computing
Requires-Python: >=3.8
License-File: LICENSE
Requires-Dist: numpy>=1.21.0
Requires-Dist: scipy>=1.7.0
Requires-Dist: scikit-learn>=1.0.0
Requires-Dist: asyncio-mqtt>=0.11.0
Requires-Dist: aiohttp>=3.8.0
Requires-Dist: pydantic>=1.8.0
Requires-Dist: rich>=12.0.0
Requires-Dist: tqdm>=4.64.0
Requires-Dist: click>=8.0.0
Requires-Dist: python-dotenv>=0.19.0
Requires-Dist: psutil>=5.8.0
Requires-Dist: networkx>=2.6.0
Requires-Dist: faiss-cpu>=1.7.0
Requires-Dist: transformers>=4.20.0
Requires-Dist: torch>=1.12.0
Requires-Dist: sentence-transformers>=2.2.0
Provides-Extra: dev
Requires-Dist: pytest>=7.0.0; extra == "dev"
Requires-Dist: pytest-asyncio>=0.21.0; extra == "dev"
Requires-Dist: pytest-cov>=4.0.0; extra == "dev"
Requires-Dist: black>=22.0.0; extra == "dev"
Requires-Dist: isort>=5.10.0; extra == "dev"
Requires-Dist: flake8>=5.0.0; extra == "dev"
Requires-Dist: mypy>=0.991; extra == "dev"
Requires-Dist: pre-commit>=2.20.0; extra == "dev"
Provides-Extra: docs
Requires-Dist: sphinx>=5.0.0; extra == "docs"
Requires-Dist: sphinx-rtd-theme>=1.0.0; extra == "docs"
Requires-Dist: myst-parser>=0.18.0; extra == "docs"
Provides-Extra: gpu
Requires-Dist: faiss-gpu>=1.7.0; extra == "gpu"
Requires-Dist: torch>=1.12.0; extra == "gpu"
Provides-Extra: all
Requires-Dist: safla[dev,docs,gpu]; extra == "all"
Dynamic: license-file
